fadvi/__init__.py
fadvi/_fadvae.py
fadvi/_fadvi.py
fadvi-0.2.0.dist-info/licenses/LICENSE
fadvi-0.2.0.dist-info/METADATA
fadvi-0.2.0.dist-info/WHEEL
fadvi-0.2.0.dist-info/top_level.txt
fadvi-0.2.0.dist-info/RECORD
