Metadata-Version: 2.4
Name: fadvi
Version: 0.2.0
Summary: Factor Disentanglement Variational Inference for single-cell batch integration with interpretability analysis
Author-email: Wendao Liu <liuwd15@gmail.com>
Maintainer-email: Wendao Liu <liuwd15@gmail.com>
License: MIT
Project-URL: Homepage, https://github.com/liuwd15/fadvi
Project-URL: Repository, https://github.com/liuwd15/fadvi
Project-URL: Documentation, https://fadvi.readthedocs.io
Project-URL: Bug Tracker, https://github.com/liuwd15/fadvi/issues
Keywords: single-cell,genomics,variational-inference,deep-learning,batch-correction,disentanglement,interpretability,feature-attribution
Classifier: Development Status :: 3 - Alpha
Classifier: Intended Audience :: Science/Research
Classifier: License :: OSI Approved :: MIT License
Classifier: Operating System :: OS Independent
Classifier: Programming Language :: Python :: 3
Classifier: Programming Language :: Python :: 3.10
Classifier: Programming Language :: Python :: 3.11
Classifier: Programming Language :: Python :: 3.12
Classifier: Programming Language :: Python :: 3.13
Classifier: Topic :: Scientific/Engineering :: Bio-Informatics
Classifier: Topic :: Scientific/Engineering :: Artificial Intelligence
Requires-Python: >=3.10
License-File: LICENSE
Requires-Dist: scvi-tools>=1.3.0
Requires-Dist: torch>=1.12.0
Requires-Dist: numpy>=1.21.0
Requires-Dist: pandas>=1.3.0
Requires-Dist: scanpy>=1.8.0
Requires-Dist: anndata>=0.8.0
Requires-Dist: scikit-learn>=1.0.0
Requires-Dist: matplotlib>=3.5.0
Requires-Dist: torchmetrics>=0.10.0
Provides-Extra: interpretability
Requires-Dist: captum>=0.6.0; extra == "interpretability"
Provides-Extra: dev
Requires-Dist: pytest>=6.0; extra == "dev"
Requires-Dist: pytest-cov; extra == "dev"
Requires-Dist: black; extra == "dev"
Requires-Dist: isort; extra == "dev"
Requires-Dist: flake8; extra == "dev"
Requires-Dist: captum>=0.6.0; extra == "dev"
Provides-Extra: docs
Requires-Dist: sphinx; extra == "docs"
Requires-Dist: sphinx-rtd-theme; extra == "docs"
Requires-Dist: nbsphinx; extra == "docs"
Requires-Dist: pandoc; extra == "docs"
Dynamic: license-file
